signed_bin_dir/__init__.py
signed_bin_dir/cli.py
signed_bin_dir/installer.py
signed_bin_dir/path_manager.py
signed_bin_dir/signer.py
signed_bin_dir-0.1.4.data/data/share/signed-bin-dir/shell_integrations/signed_bin_dir.bash
signed_bin_dir-0.1.4.data/data/share/signed-bin-dir/shell_integrations/signed_bin_dir.fish
signed_bin_dir-0.1.4.dist-info/METADATA
signed_bin_dir-0.1.4.dist-info/WHEEL
signed_bin_dir-0.1.4.dist-info/entry_points.txt
signed_bin_dir-0.1.4.dist-info/licenses/LICENSE
signed_bin_dir-0.1.4.dist-info/RECORD
