Metadata-Version: 2.4
Name: signed-bin-dir
Version: 0.1.4
Summary: Secure tool signing system for automatically adding project-specific tools to PATH
Project-URL: Homepage, https://github.com/igutekunst/signed-bin-dir
Project-URL: Repository, https://github.com/igutekunst/signed-bin-dir
Author-email: Isaac Harrison Gutekunst <isaac@supercortex.io>
License-File: LICENSE
Classifier: Development Status :: 3 - Alpha
Classifier: Intended Audience :: Developers
Classifier: License :: OSI Approved :: MIT License
Classifier: Programming Language :: Python :: 3
Classifier: Programming Language :: Python :: 3.8
Classifier: Programming Language :: Python :: 3.9
Classifier: Programming Language :: Python :: 3.10
Classifier: Programming Language :: Python :: 3.11
Classifier: Programming Language :: Python :: 3.12
Requires-Python: >=3.8
Requires-Dist: click>=8.0.0
Requires-Dist: cryptography>=41.0.0
Provides-Extra: dev
Requires-Dist: black>=23.0.0; extra == 'dev'
Requires-Dist: isort>=5.0.0; extra == 'dev'
Requires-Dist: mypy>=1.0.0; extra == 'dev'
Requires-Dist: pytest>=7.0.0; extra == 'dev'
